.VERSION
AUTHORS.rst
CONTRIBUTING.rst
HISTORY.rst
LICENSE
MANIFEST.in
Pipfile
Pipfile.lock
README.rst
USAGE.rst
dev-requirements.txt
requirements.txt
setup.cfg
setup.py
docs/Makefile
docs/authors.rst
docs/conf.py
docs/contributing.rst
docs/history.rst
docs/index.rst
docs/installation.rst
docs/readme.rst
docs/usage.rst
tests/test_wikiseriesvincentlib.py
wikiseriesvincentlib/.VERSION
wikiseriesvincentlib/AUTHORS.rst
wikiseriesvincentlib/CONTRIBUTING.rst
wikiseriesvincentlib/HISTORY.rst
wikiseriesvincentlib/LICENSE
wikiseriesvincentlib/Pipfile
wikiseriesvincentlib/Pipfile.lock
wikiseriesvincentlib/README.rst
wikiseriesvincentlib/USAGE.rst
wikiseriesvincentlib/__init__.py
wikiseriesvincentlib/_version.py
wikiseriesvincentlib/dev-requirements.txt
wikiseriesvincentlib/requirements.txt
wikiseriesvincentlib/wikiseriesvincentlib.py
wikiseriesvincentlib/wikiseriesvincentlibexceptions.py
wikiseriesvincentlib.egg-info/PKG-INFO
wikiseriesvincentlib.egg-info/SOURCES.txt
wikiseriesvincentlib.egg-info/dependency_links.txt
wikiseriesvincentlib.egg-info/not-zip-safe
wikiseriesvincentlib.egg-info/requires.txt
wikiseriesvincentlib.egg-info/top_level.txt