Metadata-Version: 2.1
Name: wikiseriesvincentlib
Version: 0.0.0
Summary: [a view of series in my last life]
Home-page: https://github.com/costastf/wikiseriesvincentlib
Author: WikiseriesVincent
Author-email: costas.tyf@gmail.com
License: MIT
Keywords: wikiseriesvincentlib
Classifier: Development Status :: 3 - Alpha
Classifier: Intended Audience :: Developers
Classifier: License :: OSI Approved :: MIT License
Classifier: Natural Language :: English
Classifier: Programming Language :: Python :: 3.9
License-File: LICENSE
License-File: AUTHORS.rst
